tests/JITspeed.py
tests/__init__.py
tests/basic.py
tests/full.py
timeWarpOB/__init__.py
timeWarpOB/plotting.py
timeWarpOB/timeWarpOB.py
timeWarpOB-1.1.1.dist-info/DESCRIPTION.rst
timeWarpOB-1.1.1.dist-info/METADATA
timeWarpOB-1.1.1.dist-info/RECORD
timeWarpOB-1.1.1.dist-info/WHEEL
timeWarpOB-1.1.1.dist-info/metadata.json
timeWarpOB-1.1.1.dist-info/top_level.txt
